biotools_client/__init__.py
biotools_client/__main__.py
biotools_client/api.py
biotools_client/cli.py
biotools_client/processing.py
biotools_client/py.typed
biotools_client/version.py
biotools_client-0.0.2.dist-info/LICENSE
biotools_client-0.0.2.dist-info/METADATA
biotools_client-0.0.2.dist-info/WHEEL
biotools_client-0.0.2.dist-info/entry_points.txt
biotools_client-0.0.2.dist-info/top_level.txt
biotools_client-0.0.2.dist-info/RECORD
