Metadata-Version: 2.1
Name: biotools_client
Version: 0.0.2
Summary: An API client to bio.tools
Author-email: Charles Tapley Hoyt <cthoyt@gmail.com>
Maintainer-email: Charles Tapley Hoyt <cthoyt@gmail.com>
License: MIT License
Project-URL: Bug Tracker, https://github.com/cthoyt/biotools-client/issues
Project-URL: Homepage, https://github.com/cthoyt/biotools-client
Project-URL: Repository, https://github.com/cthoyt/biotools-client.git
Project-URL: Documentation, https://biotools_client.readthedocs.io
Keywords: snekpack,cookiecutter,elixir,bio.tools
Classifier: Development Status :: 1 - Planning
Classifier: Environment :: Console
Classifier: Intended Audience :: Developers
Classifier: License :: OSI Approved :: MIT License
Classifier: Operating System :: OS Independent
Classifier: Framework :: Pytest
Classifier: Framework :: tox
Classifier: Framework :: Sphinx
Classifier: Programming Language :: Python
Classifier: Programming Language :: Python :: 3.9
Classifier: Programming Language :: Python :: 3.10
Classifier: Programming Language :: Python :: 3.11
Classifier: Programming Language :: Python :: 3.12
Classifier: Programming Language :: Python :: 3 :: Only
Requires-Python: >=3.12
License-File: LICENSE
Requires-Dist: tqdm
Requires-Dist: requests
Requires-Dist: click
Requires-Dist: pystow
Provides-Extra: docs
Requires-Dist: sphinx >=8 ; extra == 'docs'
Requires-Dist: sphinx-rtd-theme >=3.0 ; extra == 'docs'
Requires-Dist: sphinx-click ; extra == 'docs'
Requires-Dist: sphinx-automodapi ; extra == 'docs'
Requires-Dist: autodoc-pydantic ; extra == 'docs'
Provides-Extra: tests
Requires-Dist: pytest ; extra == 'tests'
Requires-Dist: coverage ; extra == 'tests'
